[
	{
	  "Title": "whatever",
	},
	{
	  "Title": "Typing with me and Donald T.",
	},
	{
	  "Title": "Kafkaesque",
	},
	{
	  "Title": "Euclidean Geometry",
	},
	{
	  "Title": "First Take Drake",
	},
	{
	  "Title": "Pen, pencil",
	},
	{
	  "Title": "Newcastle",
	},
	{
	  "Title": "If I make this title longer it will be more likely to turn up in a search",
	},
	{
	  "Title": "I'm running out of words",
	},
	{
	  "Title": "What the hell",
	},
	{
	  "Title": "Deakin",
	},
	{
	  "Title": "Australia",
	},
	{
	  "Title": "Football",
	},
	{
	  "Title": "Storypod",
	},
	{
	  "Title": "blankstank",
	},
]